Workbook

Sheet Ads_Performance
A1: SKU | B1: Total_Impressions | C1: Total_Clicks | D1: Total_Ad_Spend | E1: Total_Ad_Sales | F1: ACOS
A2: MN-16 | B2: 200933 | C2: 1338 | D2: 2293.56 | E2: 7931.15 | F2: 0.28918379
A3: MN-15 | B3: 446663 | C3: 5623 | D3: 11204.57 | E3: 35134.43 | F3: 0.3189057
A4: MN-14 | B4: 204049 | C4: 2023 | D4: 5935.26 | E4: 18514.63 | F4: 0.32057135
A5: MN-17 | B5: 259897 | C5: 1133 | D5: 3852.35 | E5: 10431.08 | F5: 0.36931459
A6: MN-25 | B6: 776060 | C6: 6396 | D6: 28107.19 | E6: 137984.15 | F6: 0.20369869
A7: MN-13 | B7: 340607 | C7: 2783 | D7: 2782.79 | E7: 11427.05 | F7: 0.24352654
A8: MN-22 | B8: 81210 | C8: 857 | D8: 1646.95 | E8: 6086.37 | F8: 0.27059643
A9: MN-19 | B9: 149300 | C9: 1280 | D9: 2589.76 | E9: 15922.12 | F9: 0.16265171
A10: MN-37 | B10: 91210 | C10: 457 | D10: 1071.89 | E10: 3445.4 | F10: 0.31110756
A11: MN-12 | B11: 149641 | C11: 959 | D11: 1436.43 | E11: 4443.95 | F11: 0.32323271
A12: MN-26 | B12: 275521 | C12: 1617 | D12: 8107.79 | E12: 47872.83 | F12: 0.16936099
A13: MN-27 | B13: 126221 | C13: 826 | D13: 4171.37 | E13: 20260.19 | F13: 0.20588997
... A51: MN-38 | B51: 257618 | C51: 2281 | D51: 4601.9 | E51: 18146.81 | F51: 0.25359278

Sheet Competitor_Data
A1: SKU | B1: Avg_Competitor_Price | C1: Lowest_Competitor_Price | D1: Highest_Competitor_Price | E1: Competitor_Count
A2: MN-01 | B2: 36.9 | C2: 31.95 | D2: 44.9 | E2: 9
A3: MN-02 | B3: 32.5 | C3: 27.9 | D3: 39.95 | E3: 8
A4: MN-03 | B4: 35.2 | C4: 29.99 | D4: 42.5 | E4: 7
A5: MN-04 | B5: 28.4 | C5: 24.5 | D5: 35.9 | E5: 6
A6: MN-05 | B6: 23.9 | C6: 18.95 | D6: 0 | E6: 3
A7: MN-06 | B7: 15.8 | C7: 12.99 | D7: 21.5 | E7: 4
A8: MN-07 | B8: 33.5 | C8: 28.9 | D8: 41.95 | E8: 10
A9: MN-08 | B9: 31.2 | C9: 25.95 | D9: 39.9 | E9: 6
A10: MN-09 | B10: 15.6 | C10: 11.99 | D10: 22.9 | E10: 5
A11: MN-10 | B11: 20.5 | C11: 16.95 | D11: 26.9 | E11: 9
A12: MN-11 | B12: 17.8 | C12: 14.99 | D12: 23.5 | E12: 8
A13: MN-12 | B13: 21.4 | C13: 17.95 | D13: 27.9 | E13: 9
... A51: MN-50 | B51: 30.2 | C51: 24.95 | D51: 38.9 | E51: 8

Sheet Pricing_Logic
A1: SKU | B1: Base_Cost | C1: Min_Price | D1: Target_Price | E1: Avg_Competitor_Price | F1: Total_Units_Ordered | G1: Conversion_Rate | H1: Days_of_Supply | I1: Inventory_Status | J1: ACOS | K1: Returns_30D | L1: High_Returns_Flag | M1: Pricing_Decision | N1: Recommended_Price
A2: MN-25 | B2: =_xlfn.XLOOKUP(A2, Pricing_Data!A:A, Pricing_Data!H:H) -> 16 | C2: =_xlfn.XLOOKUP(A2, Pricing_Data!A:A, Pricing_Data!N:N) -> 31.272545 | D2: =_xlfn.XLOOKUP(A2, Pricing_Data!A:A, Pricing_Data!O:O) -> 31.319619 | E2: =IFERROR(_xlfn.XLOOKUP(Pricing_Logic!A2,Competitor_Data[SKU],Competitor_Data[Avg_Competitor_Price]),0) -> 35.5 | F2: =_xlfn.XLOOKUP($A2, Historical_Sales!$A:$A, Historical_Sales!$C:$C) -> 13121 | G2: =_xlfn.XLOOKUP(A2,Historical_Sales[SKU],Historical_Sales[Total Units Ordered]) -> 4471 | H2: =_xlfn.XLOOKUP($A2, Inventory_Health!$A:$A, Inventory_Health!$C:$C) -> 1645 | I2: =_xlfn.XLOOKUP($A2, Inventory_Health!$A:$A, Inventory_Health!$D:$D) -> 341 | J2: =IFERROR(_xlfn.XLOOKUP(A2,Ads_Performance[SKU],Ads_Performance[ACOS]),0) -> 0.20369869 | K2: =_xlfn.XLOOKUP($A2, 'Returns_Data'!$A:$A, 'Returns_Data'!$B:$B) -> 73 | L2: =IF(K2>30,"High Returns","Normal") -> High Returns | M2: =IF(L2="High Returns","Decrease", IF(I2="Low Stock","Increase", IF(I2="Overstock","Decrease", IF(G2<0.05,"Decrease","Keep")))) -> Decrease | N2: =IF(E2=0, VALUE(C2), MAX( IF(M2="Increase",VALUE(E2)*1.05, IF(M2="Decrease",VALUE(E2)*0.95, VALUE(E2))), VALUE(C2) )) -> 33.725
A3: MN-26 | B3: =_xlfn.XLOOKUP(A3, Pricing_Data!A:A, Pricing_Data!H:H) -> 13 | C3: =_xlfn.XLOOKUP(A3, Pricing_Data!A:A, Pricing_Data!N:N) -> 26.903808 | D3: =_xlfn.XLOOKUP(A3, Pricing_Data!A:A, Pricing_Data!O:O) -> 26.944305 | E3: =IFERROR(_xlfn.XLOOKUP(Pricing_Logic!A3,Competitor_Data[SKU],Competitor_Data[Avg_Competitor_Price]),0) -> 30.4 | F3: =_xlfn.XLOOKUP($A3, Historical_Sales!$A:$A, Historical_Sales!$C:$C) -> 2961 | G3: =_xlfn.XLOOKUP(A3,Historical_Sales[SKU],Historical_Sales[Total Units Ordered]) -> 1663 | H3: =_xlfn.XLOOKUP($A3, Inventory_Health!$A:$A, Inventory_Health!$C:$C) -> 1142 | I3: =_xlfn.XLOOKUP($A3, Inventory_Health!$A:$A, Inventory_Health!$D:$D) -> 1079 | J3: =IFERROR(_xlfn.XLOOKUP(A3,Ads_Performance[SKU],Ads_Performance[ACOS]),0) -> 0.16936099 | K3: =_xlfn.XLOOKUP($A3, 'Returns_Data'!$A:$A, 'Returns_Data'!$B:$B) -> 30 | L3: =IF(K3>30,"High Returns","Normal") -> Normal | M3: =IF(L3="High Returns","Decrease", IF(I3="Low Stock","Increase", IF(I3="Overstock","Decrease", IF(G3<0.05,"Decrease","Keep")))) -> Keep | N3: =IF(E3=0, VALUE(C3), MAX( IF(M3="Increase",VALUE(E3)*1.05, IF(M3="Decrease",VALUE(E3)*0.95, VALUE(E3))), VALUE(C3) )) -> 30.4
A4: MN-27 | B4: =_xlfn.XLOOKUP(A4, Pricing_Data!A:A, Pricing_Data!H:H) -> 11 | C4: =_xlfn.XLOOKUP(A4, Pricing_Data!A:A, Pricing_Data!N:N) -> 24.228457 | D4: =_xlfn.XLOOKUP(A4, Pricing_Data!A:A, Pricing_Data!O:O) -> 24.264927 | E4: =IFERROR(_xlfn.XLOOKUP(Pricing_Logic!A4,Competitor_Data[SKU],Competitor_Data[Avg_Competitor_Price]),0) -> 29.9 | F4: =_xlfn.XLOOKUP($A4, Historical_Sales!$A:$A, Historical_Sales!$C:$C) -> 2609 | G4: =_xlfn.XLOOKUP(A4,Historical_Sales[SKU],Historical_Sales[Total Units Ordered]) -> 1257 | H4: =_xlfn.XLOOKUP($A4, Inventory_Health!$A:$A, Inventory_Health!$C:$C) -> 838 | I4: =_xlfn.XLOOKUP($A4, Inventory_Health!$A:$A, Inventory_Health!$D:$D) -> 772 | J4: =IFERROR(_xlfn.XLOOKUP(A4,Ads_Performance[SKU],Ads_Performance[ACOS]),0) -> 0.20588997 | K4: =_xlfn.XLOOKUP($A4, 'Returns_Data'!$A:$A, 'Returns_Data'!$B:$B) -> 21 | L4: =IF(K4>30,"High Returns","Normal") -> Normal | M4: =IF(L4="High Returns","Decrease", IF(I4="Low Stock","Increase", IF(I4="Overstock","Decrease", IF(G4<0.05,"Decrease","Keep")))) -> Keep | N4: =IF(E4=0, VALUE(C4), MAX( IF(M4="Increase",VALUE(E4)*1.05, IF(M4="Decrease",VALUE(E4)*0.95, VALUE(E4))), VALUE(C4) )) -> 29.9
A5: MN-28 | B5: =_xlfn.XLOOKUP(A5, Pricing_Data!A:A, Pricing_Data!H:H) -> 11 | C5: =_xlfn.XLOOKUP(A5, Pricing_Data!A:A, Pricing_Data!N:N) -> 22.51503 | D5: =_xlfn.XLOOKUP(A5, Pricing_Data!A:A, Pricing_Data!O:O) -> 22.548921 | E5: =IFERROR(_xlfn.XLOOKUP(Pricing_Logic!A5,Competitor_Data[SKU],Competitor_Data[Avg_Competitor_Price]),0) -> 26.2 | F5: =_xlfn.XLOOKUP($A5, Historical_Sales!$A:$A, Historical_Sales!$C:$C) -> 5516 | G5: =_xlfn.XLOOKUP(A5,Historical_Sales[SKU],Historical_Sales[Total Units Ordered]) -> 2480 | H5: =_xlfn.XLOOKUP($A5, Inventory_Health!$A:$A, Inventory_Health!$C:$C) -> 1327 | I5: =_xlfn.XLOOKUP($A5, Inventory_Health!$A:$A, Inventory_Health!$D:$D) -> 1043 | J5: =IFERROR(_xlfn.XLOOKUP(A5,Ads_Performance[SKU],Ads_Performance[ACOS]),0) -> 0.22895803 | K5: =_xlfn.XLOOKUP($A5, 'Returns_Data'!$A:$A, 'Returns_Data'!$B:$B) -> 45 | L5: =IF(K5>30,"High Returns","Normal") -> High Returns | M5: =IF(L5="High Returns","Decrease", IF(I5="Low Stock","Increase", IF(I5="Overstock","Decrease", IF(G5<0.05,"Decrease","Keep")))) -> Decrease | N5: =IF(E5=0, VALUE(C5), MAX( IF(M5="Increase",VALUE(E5)*1.05, IF(M5="Decrease",VALUE(E5)*0.95, VALUE(E5))), VALUE(C5) )) -> 24.89
A6: MN-29 | B6: =_xlfn.XLOOKUP(A6, Pricing_Data!A:A, Pricing_Data!H:H) -> 8 | C6: =_xlfn.XLOOKUP(A6, Pricing_Data!A:A, Pricing_Data!N:N) -> 17.745491 | D6: =_xlfn.XLOOKUP(A6, Pricing_Data!A:A, Pricing_Data!O:O) -> 17.772203 | E6: =IFERROR(_xlfn.XLOOKUP(Pricing_Logic!A6,Competitor_Data[SKU],Competitor_Data[Avg_Competitor_Price]),0) -> 22.8 | F6: =_xlfn.XLOOKUP($A6, Historical_Sales!$A:$A, Historical_Sales!$C:$C) -> 5346 | G6: =_xlfn.XLOOKUP(A6,Historical_Sales[SKU],Historical_Sales[Total Units Ordered]) -> 1519 | H6: =_xlfn.XLOOKUP($A6, Inventory_Health!$A:$A, Inventory_Health!$C:$C) -> 924 | I6: =_xlfn.XLOOKUP($A6, Inventory_Health!$A:$A, Inventory_Health!$D:$D) -> 815 | J6: =IFERROR(_xlfn.XLOOKUP(A6,Ads_Performance[SKU],Ads_Performance[ACOS]),0) -> 0.23092147 | K6: =_xlfn.XLOOKUP($A6, 'Returns_Data'!$A:$A, 'Returns_Data'!$B:$B) -> 72 | L6: =IF(K6>30,"High Returns","Normal") -> High Returns | M6: =IF(L6="High Returns","Decrease", IF(I6="Low Stock","Increase", IF(I6="Overstock","Decrease", IF(G6<0.05,"Decrease","Keep")))) -> Decrease | N6: =IF(E6=0, VALUE(C6), MAX( IF(M6="Increase",VALUE(E6)*1.05, IF(M6="Decrease",VALUE(E6)*0.95, VALUE(E6))), VALUE(C6) )) -> 21.66
A7: MN-30 | B7: =_xlfn.XLOOKUP(A7, Pricing_Data!A:A, Pricing_Data!H:H) -> 16 | C7: =_xlfn.XLOOKUP(A7, Pricing_Data!A:A, Pricing_Data!N:N) -> 35.300601 | D7: =_xlfn.XLOOKUP(A7, Pricing_Data!A:A, Pricing_Data!O:O) -> 35.353738 | E7: =IFERROR(_xlfn.XLOOKUP(Pricing_Logic!A7,Competitor_Data[SKU],Competitor_Data[Avg_Competitor_Price]),0) -> 36.4 | F7: =_xlfn.XLOOKUP($A7, Historical_Sales!$A:$A, Historical_Sales!$C:$C) -> 3771 | G7: =_xlfn.XLOOKUP(A7,Historical_Sales[SKU],Historical_Sales[Total Units Ordered]) -> 688 | H7: =_xlfn.XLOOKUP($A7, Inventory_Health!$A:$A, Inventory_Health!$C:$C) -> 404 | I7: =_xlfn.XLOOKUP($A7, Inventory_Health!$A:$A, Inventory_Health!$D:$D) -> 254 | J7: =IFERROR(_xlfn.XLOOKUP(A7,Ads_Performance[SKU],Ads_Performance[ACOS]),0) -> 0.2613566 | K7: =_xlfn.XLOOKUP($A7, 'Returns_Data'!$A:$A, 'Returns_Data'!$B:$B) -> 8 | L7: =IF(K7>30,"High Returns","Normal") -> Normal | M7: =IF(L7="High Returns","Decrease", IF(I7="Low Stock","Increase", IF(I7="Overstock","Decrease", IF(G7<0.05,"Decrease","Keep")))) -> Keep | N7: =IF(E7=0, VALUE(C7), MAX( IF(M7="Increase",VALUE(E7)*1.05, IF(M7="Decrease",VALUE(E7)*0.95, VALUE(E7))), VALUE(C7) )) -> 36.4
A8: MN-31 | B8: =_xlfn.XLOOKUP(A8, Pricing_Data!A:A, Pricing_Data!H:H) -> 13 | C8: =_xlfn.XLOOKUP(A8, Pricing_Data!A:A, Pricing_Data!N:N) -> 26.603206 | D8: =_xlfn.XLOOKUP(A8, Pricing_Data!A:A, Pricing_Data!O:O) -> 26.643251 | E8: =IFERROR(_xlfn.XLOOKUP(Pricing_Logic!A8,Competitor_Data[SKU],Competitor_Data[Avg_Competitor_Price]),0) -> 29.8 | F8: =_xlfn.XLOOKUP($A8, Historical_Sales!$A:$A, Historical_Sales!$C:$C) -> 1584 | G8: =_xlfn.XLOOKUP(A8,Historical_Sales[SKU],Historical_Sales[Total Units Ordered]) -> 355 | H8: =_xlfn.XLOOKUP($A8, Inventory_Health!$A:$A, Inventory_Health!$C:$C) -> 300 | I8: =_xlfn.XLOOKUP($A8, Inventory_Health!$A:$A, Inventory_Health!$D:$D) -> 199 | J8: =IFERROR(_xlfn.XLOOKUP(A8,Ads_Performance[SKU],Ads_Performance[ACOS]),0) -> 0.27639789 | K8: =_xlfn.XLOOKUP($A8, 'Returns_Data'!$A:$A, 'Returns_Data'!$B:$B) -> 7 | L8: =IF(K8>30,"High Returns","Normal") -> Normal | M8: =IF(L8="High Returns","Decrease", IF(I8="Low Stock","Increase", IF(I8="Overstock","Decrease", IF(G8<0.05,"Decrease","Keep")))) -> Keep | N8: =IF(E8=0, VALUE(C8), MAX( IF(M8="Increase",VALUE(E8)*1.05, IF(M8="Decrease",VALUE(E8)*0.95, VALUE(E8))), VALUE(C8) )) -> 29.8
A9: MN-32 | B9: =_xlfn.XLOOKUP(A9, Pricing_Data!A:A, Pricing_Data!H:H) -> 11 | C9: =_xlfn.XLOOKUP(A9, Pricing_Data!A:A, Pricing_Data!N:N) -> 23.957916 | D9: =_xlfn.XLOOKUP(A9, Pricing_Data!A:A, Pricing_Data!O:O) -> 23.993979 | E9: =IFERROR(_xlfn.XLOOKUP(Pricing_Logic!A9,Competitor_Data[SKU],Competitor_Data[Avg_Competitor_Price]),0) -> 27.5 | F9: =_xlfn.XLOOKUP($A9, Historical_Sales!$A:$A, Historical_Sales!$C:$C) -> 1484 | G9: =_xlfn.XLOOKUP(A9,Historical_Sales[SKU],Historical_Sales[Total Units Ordered]) -> 533 | H9: =_xlfn.XLOOKUP($A9, Inventory_Health!$A:$A, Inventory_Health!$C:$C) -> 338 | I9: =_xlfn.XLOOKUP($A9, Inventory_Health!$A:$A, Inventory_Health!$D:$D) -> 230 | J9: =IFERROR(_xlfn.XLOOKUP(A9,Ads_Performance[SKU],Ads_Performance[ACOS]),0) -> 0.1694922 | K9: =_xlfn.XLOOKUP($A9, 'Returns_Data'!$A:$A, 'Returns_Data'!$B:$B) -> 16 | L9: =IF(K9>30,"High Returns","Normal") -> Normal | M9: =IF(L9="High Returns","Decrease", IF(I9="Low Stock","Increase", IF(I9="Overstock","Decrease", IF(G9<0.05,"Decrease","Keep")))) -> Keep | N9: =IF(E9=0, VALUE(C9), MAX( IF(M9="Increase",VALUE(E9)*1.05, IF(M9="Decrease",VALUE(E9)*0.95, VALUE(E9))), VALUE(C9) )) -> 27.5
A10: MN-33 | B10: =_xlfn.XLOOKUP(A10, Pricing_Data!A:A, Pricing_Data!H:H) -> 11 | C10: =_xlfn.XLOOKUP(A10, Pricing_Data!A:A, Pricing_Data!N:N) -> 22.204409 | D10: =_xlfn.XLOOKUP(A10, Pricing_Data!A:A, Pricing_Data!O:O) -> 22.237832 | E10: =IFERROR(_xlfn.XLOOKUP(Pricing_Logic!A10,Competitor_Data[SKU],Competitor_Data[Avg_Competitor_Price]),0) -> 0 | F10: =_xlfn.XLOOKUP($A10, Historical_Sales!$A:$A, Historical_Sales!$C:$C) -> 1184 | G10: =_xlfn.XLOOKUP(A10,Historical_Sales[SKU],Historical_Sales[Total Units Ordered]) -> 388 | H10: =_xlfn.XLOOKUP($A10, Inventory_Health!$A:$A, Inventory_Health!$C:$C) -> 326 | I10: =_xlfn.XLOOKUP($A10, Inventory_Health!$A:$A, Inventory_Health!$D:$D) -> 153 | J10: =IFERROR(_xlfn.XLOOKUP(A10,Ads_Performance[SKU],Ads_Performance[ACOS]),0) -> 0.1636051 | K10: =_xlfn.XLOOKUP($A10, 'Returns_Data'!$A:$A, 'Returns_Data'!$B:$B) -> 13 | L10: =IF(K10>30,"High Returns","Normal") -> Normal | M10: =IF(L10="High Returns","Decrease", IF(I10="Low Stock","Increase", IF(I10="Overstock","Decrease", IF(G10<0.05,"Decrease","Keep")))) -> Keep | N10: =IF(E10=0, VALUE(C10), MAX( IF(M10="Increase",VALUE(E10)*1.05, IF(M10="Decrease",VALUE(E10)*0.95, VALUE(E10))), VALUE(C10) )) -> 22.204409
A11: MN-34 | B11: =_xlfn.XLOOKUP(A11, Pricing_Data!A:A, Pricing_Data!H:H) -> 14 | C11: =_xlfn.XLOOKUP(A11, Pricing_Data!A:A, Pricing_Data!N:N) -> 28.496994 | D11: =_xlfn.XLOOKUP(A11, Pricing_Data!A:A, Pricing_Data!O:O) -> 28.53989 | E11: =IFERROR(_xlfn.XLOOKUP(Pricing_Logic!A11,Competitor_Data[SKU],Competitor_Data[Avg_Competitor_Price]),0) -> 33.8 | F11: =_xlfn.XLOOKUP($A11, Historical_Sales!$A:$A, Historical_Sales!$C:$C) -> 2106 | G11: =_xlfn.XLOOKUP(A11,Historical_Sales[SKU],Historical_Sales[Total Units Ordered]) -> 1001 | H11: =_xlfn.XLOOKUP($A11, Inventory_Health!$A:$A, Inventory_Health!$C:$C) -> 753 | I11: =_xlfn.XLOOKUP($A11, Inventory_Health!$A:$A, Inventory_Health!$D:$D) -> 498 | J11: =IFERROR(_xlfn.XLOOKUP(A11,Ads_Performance[SKU],Ads_Performance[ACOS]),0) -> 0.19423321 | K11: =_xlfn.XLOOKUP($A11, 'Returns_Data'!$A:$A, 'Returns_Data'!$B:$B) -> 14 | L11: =IF(K11>30,"High Returns","Normal") -> Normal | M11: =IF(L11="High Returns","Decrease", IF(I11="Low Stock","Increase", IF(I11="Overstock","Decrease", IF(G11<0.05,"Decrease","Keep")))) -> Keep | N11: =IF(E11=0, VALUE(C11), MAX( IF(M11="Increase",VALUE(E11)*1.05, IF(M11="Decrease",VALUE(E11)*0.95, VALUE(E11))), VALUE(C11) )) -> 33.8
A12: MN-35 | B12: =_xlfn.XLOOKUP(A12, Pricing_Data!A:A, Pricing_Data!H:H) -> 14 | C12: =_xlfn.XLOOKUP(A12, Pricing_Data!A:A, Pricing_Data!N:N) -> 28.547094 | D12: =_xlfn.XLOOKUP(A12, Pricing_Data!A:A, Pricing_Data!O:O) -> 28.590065 | E12: =IFERROR(_xlfn.XLOOKUP(Pricing_Logic!A12,Competitor_Data[SKU],Competitor_Data[Avg_Competitor_Price]),0) -> 32.9 | F12: =_xlfn.XLOOKUP($A12, Historical_Sales!$A:$A, Historical_Sales!$C:$C) -> 1418 | G12: =_xlfn.XLOOKUP(A12,Historical_Sales[SKU],Historical_Sales[Total Units Ordered]) -> 417 | H12: =_xlfn.XLOOKUP($A12, Inventory_Health!$A:$A, Inventory_Health!$C:$C) -> 267 | I12: =_xlfn.XLOOKUP($A12, Inventory_Health!$A:$A, Inventory_Health!$D:$D) -> 168 | J12: =IFERROR(_xlfn.XLOOKUP(A12,Ads_Performance[SKU],Ads_Performance[ACOS]),0) -> 0.20819786 | K12: =_xlfn.XLOOKUP($A12, 'Returns_Data'!$A:$A, 'Returns_Data'!$B:$B) -> 8 | L12: =IF(K12>30,"High Returns","Normal") -> Normal | M12: =IF(L12="High Returns","Decrease", IF(I12="Low Stock","Increase", IF(I12="Overstock","Decrease", IF(G12<0.05,"Decrease","Keep")))) -> Keep | N12: =IF(E12=0, VALUE(C12), MAX( IF(M12="Increase",VALUE(E12)*1.05, IF(M12="Decrease",VALUE(E12)*0.95, VALUE(E12))), VALUE(C12) )) -> 32.9
A13: MN-36 | B13: =_xlfn.XLOOKUP(A13, Pricing_Data!A:A, Pricing_Data!H:H) -> 11 | C13: =_xlfn.XLOOKUP(A13, Pricing_Data!A:A, Pricing_Data!N:N) -> 25.1002 | D13: =_xlfn.XLOOKUP(A13, Pricing_Data!A:A, Pricing_Data!O:O) -> 25.137983 | E13: =IFERROR(_xlfn.XLOOKUP(Pricing_Logic!A13,Competitor_Data[SKU],Competitor_Data[Avg_Competitor_Price]),0) -> 30.1 | F13: =_xlfn.XLOOKUP($A13, Historical_Sales!$A:$A, Historical_Sales!$C:$C) -> 11890 | G13: =_xlfn.XLOOKUP(A13,Historical_Sales[SKU],Historical_Sales[Total Units Ordered]) -> 2255 | H13: =_xlfn.XLOOKUP($A13, Inventory_Health!$A:$A, Inventory_Health!$C:$C) -> 1382 | I13: =_xlfn.XLOOKUP($A13, Inventory_Health!$A:$A, Inventory_Health!$D:$D) -> 784 | J13: =IFERROR(_xlfn.XLOOKUP(A13,Ads_Performance[SKU],Ads_Performance[ACOS]),0) -> 0.2904547 | K13: =_xlfn.XLOOKUP($A13, 'Returns_Data'!$A:$A, 'Returns_Data'!$B:$B) -> 36 | L13: =IF(K13>30,"High Returns","Normal") -> High Returns | M13: =IF(L13="High Returns","Decrease", IF(I13="Low Stock","Increase", IF(I13="Overstock","Decrease", IF(G13<0.05,"Decrease","Keep")))) -> Decrease | N13: =IF(E13=0, VALUE(C13), MAX( IF(M13="Increase",VALUE(E13)*1.05, IF(M13="Decrease",VALUE(E13)*0.95, VALUE(E13))), VALUE(C13) )) -> 28.595
... A26: MN-50 | B26: =_xlfn.XLOOKUP(A26, Pricing_Data!A:A, Pricing_Data!H:H) -> 14 | C26: =_xlfn.XLOOKUP(A26, Pricing_Data!A:A, Pricing_Data!N:N) -> 27.655311 | D26: =_xlfn.XLOOKUP(A26, Pricing_Data!A:A, Pricing_Data!O:O) -> 27.696939 | E26: =IFERROR(_xlfn.XLOOKUP(Pricing_Logic!A26,Competitor_Data[SKU],Competitor_Data[Avg_Competitor_Price]),0) -> 30.2 | F26: =_xlfn.XLOOKUP($A26, Historical_Sales!$A:$A, Historical_Sales!$C:$C) -> 2424 | G26: =_xlfn.XLOOKUP(A26,Historical_Sales[SKU],Historical_Sales[Total Units Ordered]) -> 361 | H26: =_xlfn.XLOOKUP($A26, Inventory_Health!$A:$A, Inventory_Health!$C:$C) -> 217 | I26: =_xlfn.XLOOKUP($A26, Inventory_Health!$A:$A, Inventory_Health!$D:$D) -> 76 | J26: =IFERROR(_xlfn.XLOOKUP(A26,Ads_Performance[SKU],Ads_Performance[ACOS]),0) -> 0.15942008 | K26: =_xlfn.XLOOKUP($A26, 'Returns_Data'!$A:$A, 'Returns_Data'!$B:$B) -> 10 | L26: =IF(K26>30,"High Returns","Normal") -> Normal | M26: =IF(L26="High Returns","Decrease", IF(I26="Low Stock","Increase", IF(I26="Overstock","Decrease", IF(G26<0.05,"Decrease","Keep")))) -> Keep | N26: =IF(E26=0, VALUE(C26), MAX( IF(M26="Increase",VALUE(E26)*1.05, IF(M26="Decrease",VALUE(E26)*0.95, VALUE(E26))), VALUE(C26) )) -> 30.2

Sheet Historical_Sales
A1: SKU | B1: Total_Sessions | C1: Total Page Views | D1: Total Units Ordered | E1: Total Sales | F1: Total Order Items | G1: Conversion_Rate
A2: MN-01 | B2: 1921 | C2: 2484 | D2: 587 | E2: 24582.01 | F2: 475 | G2: 0.30557002
A3: MN-02 | B3: 1842 | C3: 2440 | D3: 431 | E3: 15678.89 | F3: 326 | G3: 0.2339848
A4: MN-03 | B4: 859 | C4: 1135 | D4: 196 | E4: 7340.65 | F4: 152 | G4: 0.22817229
A5: MN-07 | B5: 1815 | C5: 2553 | D5: 236 | E5: 8815.03 | F5: 221 | G5: 0.13002755
A6: MN-09 | B6: 515 | C6: 670 | D6: 81 | E6: 1347.61 | F6: 72 | G6: 0.15728155
A7: MN-10 | B7: 1292 | C7: 1716 | D7: 230 | E7: 5079.01 | F7: 201 | G7: 0.17801858
A8: MN-13 | B8: 4116 | C8: 5561 | D8: 484 | E8: 11960.96 | F8: 451 | G8: 0.11758989
A9: MN-14 | B9: 4361 | C9: 6256 | D9: 1399 | E9: 41676.88 | F9: 1058 | G9: 0.32079798
A10: MN-15 | B10: 10412 | C10: 13944 | D10: 2379 | E10: 58379.78 | F10: 2169 | G10: 0.22848636
A11: MN-16 | B11: 2762 | C11: 3682 | D11: 490 | E11: 11061.32 | F11: 455 | G11: 0.17740768
A12: MN-17 | B12: 3294 | C12: 4417 | D12: 762 | E12: 23389.16 | F12: 588 | G12: 0.23132969
A13: MN-18 | B13: 2579 | C13: 3705 | D13: 819 | E13: 23184.52 | F13: 571 | G13: 0.31756495
... A51: MN-08 | B51: 168 | C51: 241 | D51: 43 | E51: 1300.99 | F51: 35 | G51: 0.25595238

Sheet Inventory_Health
A1: SKU | B1: condition | C1: total-inventory | D1: available | E1: inv-age-0-to-30-days | F1: inv-age-31-to-60-days | G1: inv-age-61-to-90-days | H1: inv-age-181-to-330-days | I1: inv-age-331-to-365-days | J1: inv-age-365-plus-days | K1: currency | L1: units-shipped-t7 | M1: units-shipped-t30 | N1: units-shipped-t60 | O1: units-shipped-t90 | P1: sell-through | Q1: item-volume | R1: volume-unit-measurement | S1: storage-type | T1: storage-volume | U1: marketplace | V1: days-of-supply | W1: weeks-of-cover-t30 | X1: weeks-of-cover-t90 | Y1: Inventory_Status
A2: MN-01 | B2: New | C2: 382 | D2: 264 | E2: 12 | F2: 261 | G2: 56 | H2: 0 | I2: 0 | J2: 0 | K2: USD | L2: 59 | M2: 203 | N2: 386 | O2: 574 | P2: 1.33 | Q2: 0.546781 | R2: cubic feet | S2: Standard | T2: 144.35018 | U2: US | V2: 47 | W2: 6 | X2: 7 | Y2: Overstock
A3: MN-02 | B3: New | C3: 306 | D3: 206 | E3: 127 | F3: 91 | G3: 17 | H3: 0 | I3: 0 | J3: 0 | K3: USD | L3: 29 | M3: 155 | N3: 261 | O3: 417 | P3: 1.56 | Q3: 0.373971 | R3: cubic feet | S3: Standard | T3: 77.038026 | U3: US | V3: 85 | W3: 7 | X3: 8 | Y3: Overstock
A4: MN-03 | B4: New | C4: 139 | D4: 95 | E4: 42 | F4: 8 | G4: 62 | H4: 0 | I4: 0 | J4: 0 | K4: USD | L4: 13 | M4: 67 | N4: 116 | O4: 179 | P4: 1.16 | Q4: 0.425846 | R4: cubic feet | S4: Standard | T4: 40.45537 | U4: US | V4: 83 | W4: 8 | X4: 9 | Y4: Overstock
A5: MN-04 | B5: New | C5: 171 | D5: 70 | E5: 3 | F5: 84 | G5: 0 | H5: 0 | I5: 0 | J5: 0 | K5: USD | L5: 18 | M5: 71 | N5: 128 | O5: 187 | P5: 1.65 | Q5: 0.375575 | R5: cubic feet | S5: Standard | T5: 26.29025 | U5: US | V5: 99 | W5: 8 | X5: 10 | Y5: Overstock
A6: MN-05 | B6: New | C6: 283 | D6: 0 | E6: 53 | F6: 141 | G6: 0 | H6: 0 | I6: 0 | J6: 0 | K6: USD | L6: 249 | M6: 491 | N6: 543 | O6: 557 | P6: 1.47 | Q6: 0.270417 | R6: cubic feet | S6: Standard | T6: 0 | U6: US | V6: 145 | W6: 0 | X6: 1 | Y6: Overstock
A7: MN-06 | B7: New | C7: 21 | D7: 1 | E7: 8 | F7: 40 | G7: 0 | H7: 0 | I7: 0 | J7: 0 | K7: USD | L7: 61 | M7: 131 | N7: 150 | O7: 173 | P7: 1.23 | Q7: 0.155234 | R7: cubic feet | S7: Standard | T7: 0.155234 | U7: US | V7: 0 | W7: 0 | X7: 0 | Y7: Low Stock
A8: MN-07 | B8: New | C8: 144 | D8: 134 | E8: 51 | F8: 45 | G8: 55 | H8: 0 | I8: 0 | J8: 0 | K8: USD | L8: 15 | M8: 95 | N8: 150 | O8: 220 | P8: 1.25 | Q8: 0.336372 | R8: cubic feet | S8: Oversize | T8: 45.073848 | U8: US | V8: 59 | W8: 5 | X8: 7 | Y8: Overstock
A9: MN-08 | B9: New | C9: 255 | D9: 95 | E9: 4 | F9: 42 | G9: 41 | H9: 17 | I9: 0 | J9: 0 | K9: USD | L9: 2 | M9: 10 | N9: 18 | O9: 36 | P9: 0.37 | Q9: 0.315957 | R9: cubic feet | S9: Standard | T9: 30.015915 | U9: US | V9: 103 | W9: 98 | X9: 89 | Y9: Overstock
A10: MN-09 | B10: New | C10: 211 | D10: 207 | E10: 3 | F10: 1 | G10: 203 | H10: 0 | I10: 0 | J10: 0 | K10: USD | L10: 3 | M10: 19 | N10: 38 | O10: 66 | P10: 0.36 | Q10: 0.108386 | R10: cubic feet | S10: Standard | T10: 22.435902 | U10: US | V10: 57 | W10: 43 | X10: 40 | Y10: Overstock
A11: MN-10 | B11: New | C11: 363 | D11: 102 | E11: 96 | F11: 10 | G11: 43 | H11: 0 | I11: 0 | J11: 0 | K11: USD | L11: 25 | M11: 122 | N11: 177 | O11: 231 | P11: 1.17 | Q11: 0.160565 | R11: cubic feet | S11: Standard | T11: 16.37763 | U11: US | V11: 150 | W11: 10 | X11: 17 | Y11: Overstock
A12: MN-11 | B12: New | C12: 230 | D12: 124 | E12: 5 | F12: 133 | G12: 0 | H12: 0 | I12: 0 | J12: 0 | K12: USD | L12: 12 | M12: 101 | N12: 141 | O12: 215 | P12: 1.43 | Q12: 0.183563 | R12: cubic feet | S12: Standard | T12: 22.761812 | U12: US | V12: 159 | W12: 8 | X12: 13 | Y12: Overstock
A13: MN-12 | B13: New | C13: 259 | D13: 87 | E13: 93 | F13: 56 | G13: 0 | H13: 0 | I13: 0 | J13: 0 | K13: USD | L13: 48 | M13: 194 | N13: 291 | O13: 354 | P13: 1.69 | Q13: 0.279394 | R13: cubic feet | S13: Standard | T13: 24.307278 | U13: US | V13: 74 | W13: 3 | X13: 6 | Y13: Overstock
... A19: MN-18 | B19: New | C19: 458 | D19: 261 | E19: 108 | F19: 225 | G19: 0 | H19: 0 | I19: 0 | J19: 0 | K19: USD | L19: 21 | M19: 273 | N19: 482 | O19: 761 | P19: 1.81 | Q19: 0.457576 | R19: cubic feet | S19: Standard | T19: 119.42734 | U19: US | V19: 90 | W19: 6 | X19: 7 | Y19: Overstock
A20: MN-19 | B20: New | D20: 342 | E20: 70 | F20: 429 | G20: 0 | H20: 0 | I20: 0 | J20: 0 | K20: USD | L20: 122 | M20: 565 | N20: 994 | O20: 1485 | P20: 1.83 | Q20: 0.636574 | R20: cubic feet | S20: Oversize | T20: 217.70831 | U20: US | V20: 15 | W20: 2 | X20: 3 | Y20: Low Stock
A21: MN-20 | B21: New | C21: 1039 | D21: 712 | E21: 159 | F21: 684 | G21: 0 | H21: 0 | I21: 0 | J21: 0 | K21: USD | L21: 124 | M21: 526 | N21: 1000 | O21: 1494 | P21: 1.15 | Q21: 0.039821 | R21: cubic feet | S21: Standard | T21: 28.352552 | U21: US | V21: 66 | W21: 7 | X21: 8 | Y21: Overstock
A22: MN-21 | B22: New | C22: 18 | D22: 2 | E22: 23 | F22: 16 | G22: 0 | H22: 0 | I22: 0 | J22: 0 | K22: USD | L22: 41 | M22: 235 | N22: 432 | O22: 553 | P22: 3.18 | Q22: 0.234841 | R22: cubic feet | S22: Standard | T22: 0.469682 | U22: US | V22: 0 | W22: 0 | X22: 0 | Y22: Low Stock
A23: MN-22 | B23: New | C23: 395 | D23: 252 | E23: 268 | F23: 63 | G23: 0 | H23: 0 | I23: 0 | J23: 0 | K23: USD | L23: 78 | M23: 355 | N23: 553 | O23: 733 | P23: 1.85 | Q23: 0.257323 | R23: cubic feet | S23: Standard | T23: 64.845396 | U23: US | V23: 51 | W23: 4 | X23: 6 | Y23: Overstock
A24: MN-23 | B24: New | C24: 547 | D24: 285 | E24: 227 | F24: 122 | G24: 0 | H24: 0 | I24: 0 | J24: 0 | K24: USD | L24: 86 | M24: 326 | N24: 496 | O24: 691 | P24: 1.64 | Q24: 0.017404 | R24: cubic feet | S24: Standard | T24: 4.96014 | U24: US | V24: 73 | W24: 6 | X24: 9 | Y24: Overstock
A25: MN-24 | B25: New | C25: 424 | D25: 292 | E25: 210 | F25: 48 | G25: 87 | H25: 0 | I25: 0 | J25: 0 | K25: USD | L25: 43 | M25: 200 | N25: 310 | O25: 468 | P25: 1.37 | Q25: 0.186266 | R25: cubic feet | S25: Standard | T25: 54.389672 | U25: US | V25: 106 | W25: 7 | X25: 10 | Y25: Overstock
A26: MN-25 | B26: New | C26: 1645 | D26: 341 | E26: 74 | F26: 482 | G26: 0 | H26: 0 | I26: 0 | J26: 0 | K26: USD | L26: 233 | M26: 1729 | N26: 3336 | O26: 4300 | P26: 3 | Q26: 0.510138 | R26: cubic feet | S26: Standard | T26: 173.95706 | U26: US | V26: 41 | W26: 3 | X26: 4 | Y26: Healthy
A27: MN-26 | B27: New | C27: 1142 | D27: 1079 | E27: 456 | F27: 756 | G27: 0 | H27: 0 | I27: 0 | J27: 0 | K27: USD | L27: 132 | M27: 515 | N27: 1026 | O27: 1596 | P27: 1.64 | Q27: 0.285126 | R27: cubic feet | S27: Standard | T27: 307.65095 | U27: US | V27: 80 | W27: 8 | X27: 8 | Y27: Overstock
A28: MN-27 | B28: New | C28: 838 | D28: 772 | E28: 696 | F28: 163 | G28: 0 | H28: 0 | I28: 0 | J28: 0 | K28: USD | L28: 129 | M28: 542 | N28: 932 | O28: 1320 | P28: 1.83 | Q28: 0.287959 | R28: cubic feet | S28: Standard | T28: 222.30435 | U28: US | V28: 82 | W28: 5 | X28: 7 | Y28: Overstock
A29: MN-28 | B29: New | C29: 1327 | D29: 1043 | E29: 55 | F29: 1202 | G29: 0 | H29: 0 | I29: 0 | J29: 0 | K29: USD | L29: 198 | M29: 767 | N29: 1586 | O29: 2404 | P29: 1.65 | Q29: 0.199538 | R29: cubic feet | S29: Standard | T29: 208.11813 | U29: US | V29: 67 | W29: 6 | X29: 6 | Y29: Overstock
A30: MN-29 | B30: New | C30: 924 | D30: 815 | E30: 260 | F30: 673 | G30: 0 | H30: 0 | I30: 0 | J30: 0 | K30: USD | L30: 132 | M30: 545 | N30: 988 | O30: 1451 | P30: 1.6 | Q30: 0.09045 | R30: cubic feet | S30: Standard | T30: 73.71675 | U30: US | V30: 77 | W30: 6 | X30: 7 | Y30: Overstock
A31: MN-30 | B31: New | C31: 404 | D31: 254 | E31: 139 | F31: 104 | G31: 68 | H31: 0 | I31: 0 | J31: 0 | K31: USD | L31: 29 | M31: 245 | N31: 423 | O31: 612 | P31: 1.44 | Q31: 0.474537 | R31: cubic feet | S31: Oversize | T31: 120.5324 | U31: US | V31: 65 | W31: 5 | X31: 7 | Y31: Overstock
A32: MN-31 | B32: New | C32: 300 | D32: 199 | E32: 15 | F32: 207 | G32: 0 | H32: 0 | I32: 0 | J32: 0 | K32: USD | L32: 24 | M32: 120 | N32: 211 | O32: 331 | P32: 1.61 | Q32: 0.304942 | R32: cubic feet | S32: Standard | T32: 60.683458 | U32: US | V32: 118 | W32: 9 | X32: 11 | Y32: Overstock
... A39: MN-38 | B39: New | C39: 991 | D39: 861 | E39: 587 | F39: 373 | G39: 0 | H39: 0 | I39: 0 | J39: 0 | K39: USD | L39: 114 | M39: 429 | N39: 954 | O39: 1509 | P39: 1.8 | Q39: 0.162883 | R39: cubic feet | S39: Standard | T39: 140.24226 | U39: US | V39: 76 | W39: 8 | X39: 8 | Y39: Overstock
A40: MN-39 | B40: New | D40: 22 | E40: 52 | F40: 2 | G40: 23 | H40: 0 | I40: 0 | J40: 0 | K40: USD | L40: 52 | M40: 157 | N40: 218 | O40: 288 | P40: 1.56 | Q40: 0.089032 | R40: cubic feet | S40: Standard | T40: 1.958704 | U40: US | V40: 95 | W40: 6 | X40: 10 | Y40: Overstock
A41: MN-40 | B41: New | C41: 655 | D41: 407 | E41: 356 | F41: 155 | G41: 0 | H41: 0 | I41: 0 | J41: 0 | K41: USD | L41: 85 | M41: 337 | N41: 613 | O41: 893 | P41: 1.74 | Q41: 0.132234 | R41: cubic feet | S41: Standard | T41: 53.819238 | U41: US | V41: 84 | W41: 6 | X41: 8 | Y41: Overstock
A42: MN-41 | B42: New | C42: 935 | D42: 694 | E42: 22 | F42: 831 | G42: 0 | H42: 0 | I42: 0 | J42: 0 | K42: USD | L42: 142 | M42: 535 | N42: 953 | O42: 1443 | P42: 1.52 | Q42: 0.643986 | R42: cubic feet | S42: Standard | T42: 446.92628 | U42: US | V42: 75 | W42: 6 | X42: 7 | Y42: Overstock
A43: MN-42 | B43: New | C43: 752 | D43: 673 | E43: 328 | F43: 206 | G43: 258 | H43: 0 | I43: 0 | J43: 0 | K43: USD | L43: 83 | M43: 252 | N43: 709 | O43: 1224 | P43: 1.42 | Q43: 0.372838 | R43: cubic feet | S43: Standard | T43: 250.91997 | U43: US | V43: 86 | W43: 10 | X43: 7 | Y43: Overstock
A44: MN-43 | B44: New | C44: 166 | D44: 123 | E44: 110 | F44: 12 | G44: 51 | H44: 0 | I44: 0 | J44: 0 | K44: USD | L44: 25 | M44: 100 | N44: 162 | O44: 217 | P44: 1.24 | Q44: 0.035586 | R44: cubic feet | S44: Standard | T44: 4.377078 | U44: US | V44: 74 | W44: 4 | X44: 7 | Y44: Overstock
A45: MN-44 | B45: New | C45: 130 | D45: 96 | E45: 69 | F45: 54 | G45: 0 | H45: 0 | I45: 0 | J45: 0 | K45: USD | L45: 14 | M45: 57 | N45: 96 | O45: 133 | P45: 0.85 | Q45: 0.034594 | R45: cubic feet | S45: Standard | T45: 3.321024 | U45: US | V45: 99 | W45: 7 | X45: 11 | Y45: Overstock
A46: MN-45 | B46: New | C46: 159 | D46: 82 | E46: 51 | F46: 55 | G46: 0 | H46: 0 | I46: 0 | J46: 0 | K46: USD | L46: 20 | M46: 71 | N46: 204 | O46: 328 | P46: 2.02 | Q46: 0.103417 | R46: cubic feet | S46: Standard | T46: 8.480194 | U46: US | V46: 63 | W46: 8 | X46: 5 | Y46: Overstock
A47: MN-46 | B47: New | C47: 177 | D47: 109 | E47: 77 | F47: 52 | G47: 0 | H47: 0 | I47: 0 | J47: 0 | K47: USD | L47: 19 | M47: 78 | N47: 117 | O47: 173 | P47: 1.4 | Q47: 0.082992 | R47: cubic feet | S47: Standard | T47: 9.046128 | U47: US | V47: 103 | W47: 8 | X47: 12 | Y47: Overstock
A48: MN-47 | B48: New | C48: 256 | D48: 241 | E48: 11 | F48: 82 | G48: 169 | H48: 0 | I48: 0 | J48: 0 | K48: USD | L48: 12 | M48: 54 | N48: 158 | O48: 271 | P48: 0.96 | Q48: 0.474597 | R48: cubic feet | S48: Standard | T48: 114.37788 | U48: US | V48: 89 | W48: 17 | X48: 11 | Y48: Overstock
A49: MN-48 | B49: New | C49: 210 | D49: 196 | E49: 1 | F49: 163 | G49: 45 | H49: 0 | I49: 0 | J49: 0 | K49: USD | L49: 26 | M49: 67 | N49: 158 | O49: 265 | P49: 1.19 | Q49: 0.91242 | R49: cubic feet | S49: Standard | T49: 178.83432 | U49: US | V49: 84 | W49: 11 | X49: 9 | Y49: Overstock
A50: MN-49 | B50: New | C50: 196 | D50: 156 | E50: 10 | F50: 182 | G50: 0 | H50: 0 | I50: 0 | J50: 0 | K50: USD | L50: 30 | M50: 129 | N50: 277 | O50: 404 | P50: 1.89 | Q50: 0.37674 | R50: cubic feet | S50: Standard | T50: 58.77144 | U50: US | V50: 40 | W50: 5 | X50: 5 | Y50: Healthy
A51: MN-50 | B51: New | C51: 217 | D51: 76 | E51: 89 | F51: 86 | G51: 0 | H51: 0 | I51: 0 | J51: 0 | K51: USD | L51: 49 | M51: 148 | N51: 254 | O51: 378 | P51: 1.92 | Q51: 0.336525 | R51: cubic feet | S51: Standard | T51: 25.5759 | U51: US | V51: 49 | W51: 3 | X51: 4 | Y51: Overstock

Sheet Returns_Data
A1: SKU | B1: Return Quantity (Last 30 days) | C1: High_Returns_Flag
A2: MN-01 | B2: 9 | C2: Normal
A3: MN-02 | B3: 4 | C3: Normal
A4: MN-03 | B4: 4 | C4: Normal
A5: MN-04 | B5: 4 | C5: Normal
A6: MN-09 | B6: 2 | C6: Normal
A7: MN-08 | B7: 3 | C7: Normal
A8: MN-10 | B8: 9 | C8: Normal
A9: MN-11 | B9: 6 | C9: Normal
A10: MN-12 | B10: 13 | C10: Normal
A11: MN-13 | B11: 4 | C11: Normal
A12: MN-14 | B12: 79 | C12: Normal
A13: MN-15 | B13: 44 | C13: Normal
... A51: MN-06 | B51: 2 | C51: Normal

Sheet Pricing_Data
A1: SKU | B1: Product_description | C1: Product Role | D1: Country_of_Origin | E1: FBA Fee | F1: Storage Fee | G1: Handling_Cost | H1: Cost | I1: Current_Price | J1: Minimum_Acceptable_Margin_% | K1: Target_Gross_Margin_% | L1: Total_Fees | M1: Base_Cost | N1: Min_Price | O1: CustTarget_Price
A2: MN-01 | B2: Rectangle Tray -14 x 10 Inch - Pk of 25 | C2: Core | D2: India | E2: 15.11 | F2: 0.44 | G2: 0.75 | H2: 16 | I2: $38.90 | J2: 0.2 | K2: 0.35 | L2: 16.3 | M2: 32.3 | N2: 32.364729 | O2: 32.413447
A3: MN-02 | B3: Rectangle Tray -12x10 - Pk of 25 | C3: Core | D3: India | E3: 13.55 | F3: 0.3 | G3: 0.75 | H3: 12 | I3: $33.90 | J3: 0.2 | K3: 0.35 | L3: 14.6 | M3: 26.6 | N3: 26.653307 | O3: 26.693427
A4: MN-03 | B4: Oval Tray -15x10 Inch - Pk of 25 | C4: Core | D4: India | E4: 13.94 | F4: 0.34 | G4: 0.75 | H4: 15 | I4: $34.90 | J4: 0.2 | K4: 0.35 | L4: 15.03 | M4: 30.03 | N4: 30.09018 | O4: 30.135474
A5: MN-04 | B5: Oval Tray - 13x9 Inch - pk of 25 | C5: Core | D5: India | E5: 12.89 | F5: 0.3 | G5: 0.75 | H5: 12 | I5: $29.90 | J5: 0.2 | K5: 0.35 | L5: 13.94 | M5: 25.94 | N5: 25.991984 | O5: 26.031109
A6: MN-05 | B6: Christmas Tray - 17x12 Inch - Pk of 5 | C6: Seasonal | D6: India | E6: 11.8 | F6: 0.22 | G6: 0.75 | H6: 13 | I6: $21.90 | J6: 0.25 | K6: 0.45 | L6: 12.77 | M6: 25.77 | N6: 25.834586 | O6: 25.886489
A7: MN-06 | B7: Star Tray - 14 Inch - Pk of 5 | C7: Seasonal | D7: India | E7: 8.5 | F7: 0.12 | G7: 0.75 | H7: 5 | I7: $14.95 | J7: 0.25 | K7: 0.45 | L7: 9.37 | M7: 14.37 | N7: 14.406015 | O7: 14.434957
A8: MN-07 | B8: 15 Round plate - pk of 10 | C8: Core | D8: India | E8: 17.85 | F8: 0.27 | G8: 0.75 | H8: 11 | I8: $34.90 | J8: 0.2 | K8: 0.35 | L8: 18.87 | M8: 29.87 | N8: 29.92986 | O8: 29.974912
A9: MN-08 | B9: 10 Inch Heart Plates - pk of 25 | C9: Seasonal | D9: India | E9: 12.11 | F9: 0.25 | G9: 0.75 | H9: 13 | I9: $29.90 | J9: 0.25 | K9: 0.45 | L9: 13.11 | M9: 26.11 | N9: 26.175439 | O9: 26.228026
A10: MN-09 | B10: 6 Inch Heart Plates - pk of 25 | C10: Seasonal | D10: India | E10: 8.08 | F10: 0.09 | G10: 0.75 | H10: 6 | I10: $14.90 | J10: 0.25 | K10: 0.45 | L10: 8.92 | M10: 14.92 | N10: 14.957393 | O10: 14.987443
A11: MN-10 | B11: 9x6 Rectangle - pk of 25 | C11: Core | D11: India | E11: 9.52 | F11: 0.13 | G11: 0.75 | H11: 7 | I11: $19.90 | J11: 0.2 | K11: 0.35 | L11: 10.4 | M11: 17.4 | N11: 17.43487 | O11: 17.461114
A12: MN-11 | B12: Oval Tray - 13x9 Inch - pk of 10 | C12: Core | D12: India | E12: 9.36 | F12: 0.15 | G12: 0.75 | H12: 5 | I12: $16.90 | J12: 0.2 | K12: 0.35 | L12: 10.26 | M12: 15.26 | N12: 15.290581 | O12: 15.313598
A13: MN-12 | B13: 13 inch Round DEEP plate - pk of 10 | C13: Core | D13: India | E13: 10.9 | F13: 0.22 | G13: 0.75 | H13: 6 | I13: $19.90 | J13: 0.2 | K13: 0.35 | L13: 11.87 | M13: 17.87 | N13: 17.905812 | O13: 17.932765
... A50: MN-50 | B50: 9x6 Rectangle - pk of 50 | C50: Core | D50: India | E50: 12.58 | F50: 0.27 | G50: 0.75 | H50: 14 | I50: $29.90 | J50: 0.2 | K50: 0.35 | L50: 13.6 | M50: 27.6 | N50: 27.655311 | O50: 27.696939

Sheet Sheet2

Sheet Sheet1
